{
  "loader": "antimatter:dynamic",
  "config": [
    {
      "id": 1989,
      "models": [
        {
          "parent": "antimatter:block/preset/simple_overlay",
          "textures": {
            "base": "gti:block/ct/turbine/large_turbine_0"
          },
          "rotation": [
            0,
            0,
            0
          ]
        }
      ]
    },
    {
      "id": 11989,
      "models": [
        {
          "parent": "antimatter:block/preset/simple_overlay",
          "textures": {
            "base": "gti:block/ct/turbine/large_turbine_active_0"
          },
          "rotation": [
            0,
            0,
            0
          ]
        }
      ]
    },
    {
      "id": 1990,
      "models": [
        {
          "parent": "antimatter:block/preset/simple_overlay",
          "textures": {
            "base": "gti:block/ct/turbine/large_turbine_1"
          },
          "rotation": [
            0,
            0,
            0
          ]
        }
      ]
    },
    {
      "id": 11990,
      "models": [
        {
          "parent": "antimatter:block/preset/simple_overlay",
          "textures": {
            "base": "gti:block/ct/turbine/large_turbine_active_1"
          },
          "rotation": [
            0,
            0,
            0
          ]
        }
      ]
    },
    {
      "id": 1991,
      "models": [
        {
          "parent": "antimatter:block/preset/simple_overlay",
          "textures": {
            "base": "gti:block/ct/turbine/large_turbine_2"
          },
          "rotation": [
            0,
            0,
            0
          ]
        }
      ]
    },
    {
      "id": 11991,
      "models": [
        {
          "parent": "antimatter:block/preset/simple_overlay",
          "textures": {
            "base": "gti:block/ct/turbine/large_turbine_active_2"
          },
          "rotation": [
            0,
            0,
            0
          ]
        }
      ]
    },
    {
      "id": 1999,
      "models": [
        {
          "parent": "antimatter:block/preset/simple_overlay",
          "textures": {
            "base": "gti:block/ct/turbine/large_turbine_3"
          },
          "rotation": [
            0,
            0,
            0
          ]
        }
      ]
    },
    {
      "id": 11999,
      "models": [
        {
          "parent": "antimatter:block/preset/simple_overlay",
          "textures": {
            "base": "gti:block/ct/turbine/large_turbine_active_3"
          },
          "rotation": [
            0,
            0,
            0
          ]
        }
      ]
    },
    {
      "id": 2001,
      "models": [
        {
          "parent": "antimatter:block/preset/simple_overlay",
          "textures": {
            "base": "gti:block/ct/turbine/large_turbine_5"
          },
          "rotation": [
            0,
            0,
            0
          ]
        }
      ]
    },
    {
      "id": 12001,
      "models": [
        {
          "parent": "antimatter:block/preset/simple_overlay",
          "textures": {
            "base": "gti:block/ct/turbine/large_turbine_active_5"
          },
          "rotation": [
            0,
            0,
            0
          ]
        }
      ]
    },
    {
      "id": 2009,
      "models": [
        {
          "parent": "antimatter:block/preset/simple_overlay",
          "textures": {
            "base": "gti:block/ct/turbine/large_turbine_6"
          },
          "rotation": [
            0,
            0,
            0
          ]
        }
      ]
    },
    {
      "id": 12009,
      "models": [
        {
          "parent": "antimatter:block/preset/simple_overlay",
          "textures": {
            "base": "gti:block/ct/turbine/large_turbine_active_6"
          },
          "rotation": [
            0,
            0,
            0
          ]
        }
      ]
    },
    {
      "id": 2010,
      "models": [
        {
          "parent": "antimatter:block/preset/simple_overlay",
          "textures": {
            "base": "gti:block/ct/turbine/large_turbine_7"
          },
          "rotation": [
            0,
            0,
            0
          ]
        }
      ]
    },
    {
      "id": 12010,
      "models": [
        {
          "parent": "antimatter:block/preset/simple_overlay",
          "textures": {
            "base": "gti:block/ct/turbine/large_turbine_active_7"
          },
          "rotation": [
            0,
            0,
            0
          ]
        }
      ]
    },
    {
      "id": 2011,
      "models": [
        {
          "parent": "antimatter:block/preset/simple_overlay",
          "textures": {
            "base": "gti:block/ct/turbine/large_turbine_8"
          },
          "rotation": [
            0,
            0,
            0
          ]
        }
      ]
    },
    {
      "id": 12011,
      "models": [
        {
          "parent": "antimatter:block/preset/simple_overlay",
          "textures": {
            "base": "gti:block/ct/turbine/large_turbine_active_8"
          },
          "rotation": [
            0,
            0,
            0
          ]
        }
      ]
    },
    {
      "id": 4890,
      "models": [
        {
          "parent": "antimatter:block/preset/simple_overlay",
          "textures": {
            "base": "gti:block/ct/turbine/large_turbine_0"
          },
          "rotation": [
            0,
            270,
            0
          ]
        }
      ]
    },
    {
      "id": 14890,
      "models": [
        {
          "parent": "antimatter:block/preset/simple_overlay",
          "textures": {
            "base": "gti:block/ct/turbine/large_turbine_active_0"
          },
          "rotation": [
            0,
            270,
            0
          ]
        }
      ]
    },
    {
      "id": 4990,
      "models": [
        {
          "parent": "antimatter:block/preset/simple_overlay",
          "textures": {
            "base": "gti:block/ct/turbine/large_turbine_1"
          },
          "rotation": [
            0,
            270,
            0
          ]
        }
      ]
    },
    {
      "id": 14990,
      "models": [
        {
          "parent": "antimatter:block/preset/simple_overlay",
          "textures": {
            "base": "gti:block/ct/turbine/large_turbine_active_1"
          },
          "rotation": [
            0,
            270,
            0
          ]
        }
      ]
    },
    {
      "id": 5090,
      "models": [
        {
          "parent": "antimatter:block/preset/simple_overlay",
          "textures": {
            "base": "gti:block/ct/turbine/large_turbine_2"
          },
          "rotation": [
            0,
            270,
            0
          ]
        }
      ]
    },
    {
      "id": 15090,
      "models": [
        {
          "parent": "antimatter:block/preset/simple_overlay",
          "textures": {
            "base": "gti:block/ct/turbine/large_turbine_active_2"
          },
          "rotation": [
            0,
            270,
            0
          ]
        }
      ]
    },
    {
      "id": 4900,
      "models": [
        {
          "parent": "antimatter:block/preset/simple_overlay",
          "textures": {
            "base": "gti:block/ct/turbine/large_turbine_3"
          },
          "rotation": [
            0,
            270,
            0
          ]
        }
      ]
    },
    {
      "id": 14900,
      "models": [
        {
          "parent": "antimatter:block/preset/simple_overlay",
          "textures": {
            "base": "gti:block/ct/turbine/large_turbine_active_3"
          },
          "rotation": [
            0,
            270,
            0
          ]
        }
      ]
    },
    {
      "id": 5100,
      "models": [
        {
          "parent": "antimatter:block/preset/simple_overlay",
          "textures": {
            "base": "gti:block/ct/turbine/large_turbine_5"
          },
          "rotation": [
            0,
            270,
            0
          ]
        }
      ]
    },
    {
      "id": 15100,
      "models": [
        {
          "parent": "antimatter:block/preset/simple_overlay",
          "textures": {
            "base": "gti:block/ct/turbine/large_turbine_active_5"
          },
          "rotation": [
            0,
            270,
            0
          ]
        }
      ]
    },
    {
      "id": 4910,
      "models": [
        {
          "parent": "antimatter:block/preset/simple_overlay",
          "textures": {
            "base": "gti:block/ct/turbine/large_turbine_6"
          },
          "rotation": [
            0,
            270,
            0
          ]
        }
      ]
    },
    {
      "id": 14910,
      "models": [
        {
          "parent": "antimatter:block/preset/simple_overlay",
          "textures": {
            "base": "gti:block/ct/turbine/large_turbine_active_6"
          },
          "rotation": [
            0,
            270,
            0
          ]
        }
      ]
    },
    {
      "id": 5010,
      "models": [
        {
          "parent": "antimatter:block/preset/simple_overlay",
          "textures": {
            "base": "gti:block/ct/turbine/large_turbine_7"
          },
          "rotation": [
            0,
            270,
            0
          ]
        }
      ]
    },
    {
      "id": 15010,
      "models": [
        {
          "parent": "antimatter:block/preset/simple_overlay",
          "textures": {
            "base": "gti:block/ct/turbine/large_turbine_active_7"
          },
          "rotation": [
            0,
            270,
            0
          ]
        }
      ]
    },
    {
      "id": 5110,
      "models": [
        {
          "parent": "antimatter:block/preset/simple_overlay",
          "textures": {
            "base": "gti:block/ct/turbine/large_turbine_8"
          },
          "rotation": [
            0,
            270,
            0
          ]
        }
      ]
    },
    {
      "id": 15110,
      "models": [
        {
          "parent": "antimatter:block/preset/simple_overlay",
          "textures": {
            "base": "gti:block/ct/turbine/large_turbine_active_8"
          },
          "rotation": [
            0,
            270,
            0
          ]
        }
      ]
    },
    {
      "id": 2991,
      "models": [
        {
          "parent": "antimatter:block/preset/simple_overlay",
          "textures": {
            "base": "gti:block/ct/turbine/large_turbine_0"
          },
          "rotation": [
            0,
            180,
            0
          ]
        }
      ]
    },
    {
      "id": 12991,
      "models": [
        {
          "parent": "antimatter:block/preset/simple_overlay",
          "textures": {
            "base": "gti:block/ct/turbine/large_turbine_active_0"
          },
          "rotation": [
            0,
            180,
            0
          ]
        }
      ]
    },
    {
      "id": 2990,
      "models": [
        {
          "parent": "antimatter:block/preset/simple_overlay",
          "textures": {
            "base": "gti:block/ct/turbine/large_turbine_1"
          },
          "rotation": [
            0,
            180,
            0
          ]
        }
      ]
    },
    {
      "id": 12990,
      "models": [
        {
          "parent": "antimatter:block/preset/simple_overlay",
          "textures": {
            "base": "gti:block/ct/turbine/large_turbine_active_1"
          },
          "rotation": [
            0,
            180,
            0
          ]
        }
      ]
    },
    {
      "id": 2989,
      "models": [
        {
          "parent": "antimatter:block/preset/simple_overlay",
          "textures": {
            "base": "gti:block/ct/turbine/large_turbine_2"
          },
          "rotation": [
            0,
            180,
            0
          ]
        }
      ]
    },
    {
      "id": 12989,
      "models": [
        {
          "parent": "antimatter:block/preset/simple_overlay",
          "textures": {
            "base": "gti:block/ct/turbine/large_turbine_active_2"
          },
          "rotation": [
            0,
            180,
            0
          ]
        }
      ]
    },
    {
      "id": 3001,
      "models": [
        {
          "parent": "antimatter:block/preset/simple_overlay",
          "textures": {
            "base": "gti:block/ct/turbine/large_turbine_3"
          },
          "rotation": [
            0,
            180,
            0
          ]
        }
      ]
    },
    {
      "id": 13001,
      "models": [
        {
          "parent": "antimatter:block/preset/simple_overlay",
          "textures": {
            "base": "gti:block/ct/turbine/large_turbine_active_3"
          },
          "rotation": [
            0,
            180,
            0
          ]
        }
      ]
    },
    {
      "id": 2999,
      "models": [
        {
          "parent": "antimatter:block/preset/simple_overlay",
          "textures": {
            "base": "gti:block/ct/turbine/large_turbine_5"
          },
          "rotation": [
            0,
            180,
            0
          ]
        }
      ]
    },
    {
      "id": 12999,
      "models": [
        {
          "parent": "antimatter:block/preset/simple_overlay",
          "textures": {
            "base": "gti:block/ct/turbine/large_turbine_active_5"
          },
          "rotation": [
            0,
            180,
            0
          ]
        }
      ]
    },
    {
      "id": 3011,
      "models": [
        {
          "parent": "antimatter:block/preset/simple_overlay",
          "textures": {
            "base": "gti:block/ct/turbine/large_turbine_6"
          },
          "rotation": [
            0,
            180,
            0
          ]
        }
      ]
    },
    {
      "id": 13011,
      "models": [
        {
          "parent": "antimatter:block/preset/simple_overlay",
          "textures": {
            "base": "gti:block/ct/turbine/large_turbine_active_6"
          },
          "rotation": [
            0,
            180,
            0
          ]
        }
      ]
    },
    {
      "id": 3010,
      "models": [
        {
          "parent": "antimatter:block/preset/simple_overlay",
          "textures": {
            "base": "gti:block/ct/turbine/large_turbine_7"
          },
          "rotation": [
            0,
            180,
            0
          ]
        }
      ]
    },
    {
      "id": 13010,
      "models": [
        {
          "parent": "antimatter:block/preset/simple_overlay",
          "textures": {
            "base": "gti:block/ct/turbine/large_turbine_active_7"
          },
          "rotation": [
            0,
            180,
            0
          ]
        }
      ]
    },
    {
      "id": 3009,
      "models": [
        {
          "parent": "antimatter:block/preset/simple_overlay",
          "textures": {
            "base": "gti:block/ct/turbine/large_turbine_8"
          },
          "rotation": [
            0,
            180,
            0
          ]
        }
      ]
    },
    {
      "id": 13009,
      "models": [
        {
          "parent": "antimatter:block/preset/simple_overlay",
          "textures": {
            "base": "gti:block/ct/turbine/large_turbine_active_8"
          },
          "rotation": [
            0,
            180,
            0
          ]
        }
      ]
    },
    {
      "id": 4090,
      "models": [
        {
          "parent": "antimatter:block/preset/simple_overlay",
          "textures": {
            "base": "gti:block/ct/turbine/large_turbine_0"
          },
          "rotation": [
            0,
            90,
            0
          ]
        }
      ]
    },
    {
      "id": 14090,
      "models": [
        {
          "parent": "antimatter:block/preset/simple_overlay",
          "textures": {
            "base": "gti:block/ct/turbine/large_turbine_active_0"
          },
          "rotation": [
            0,
            90,
            0
          ]
        }
      ]
    },
    {
      "id": 3990,
      "models": [
        {
          "parent": "antimatter:block/preset/simple_overlay",
          "textures": {
            "base": "gti:block/ct/turbine/large_turbine_1"
          },
          "rotation": [
            0,
            90,
            0
          ]
        }
      ]
    },
    {
      "id": 13990,
      "models": [
        {
          "parent": "antimatter:block/preset/simple_overlay",
          "textures": {
            "base": "gti:block/ct/turbine/large_turbine_active_1"
          },
          "rotation": [
            0,
            90,
            0
          ]
        }
      ]
    },
    {
      "id": 3890,
      "models": [
        {
          "parent": "antimatter:block/preset/simple_overlay",
          "textures": {
            "base": "gti:block/ct/turbine/large_turbine_2"
          },
          "rotation": [
            0,
            90,
            0
          ]
        }
      ]
    },
    {
      "id": 13890,
      "models": [
        {
          "parent": "antimatter:block/preset/simple_overlay",
          "textures": {
            "base": "gti:block/ct/turbine/large_turbine_active_2"
          },
          "rotation": [
            0,
            90,
            0
          ]
        }
      ]
    },
    {
      "id": 4100,
      "models": [
        {
          "parent": "antimatter:block/preset/simple_overlay",
          "textures": {
            "base": "gti:block/ct/turbine/large_turbine_3"
          },
          "rotation": [
            0,
            90,
            0
          ]
        }
      ]
    },
    {
      "id": 14100,
      "models": [
        {
          "parent": "antimatter:block/preset/simple_overlay",
          "textures": {
            "base": "gti:block/ct/turbine/large_turbine_active_3"
          },
          "rotation": [
            0,
            90,
            0
          ]
        }
      ]
    },
    {
      "id": 3900,
      "models": [
        {
          "parent": "antimatter:block/preset/simple_overlay",
          "textures": {
            "base": "gti:block/ct/turbine/large_turbine_5"
          },
          "rotation": [
            0,
            90,
            0
          ]
        }
      ]
    },
    {
      "id": 13900,
      "models": [
        {
          "parent": "antimatter:block/preset/simple_overlay",
          "textures": {
            "base": "gti:block/ct/turbine/large_turbine_active_5"
          },
          "rotation": [
            0,
            90,
            0
          ]
        }
      ]
    },
    {
      "id": 4110,
      "models": [
        {
          "parent": "antimatter:block/preset/simple_overlay",
          "textures": {
            "base": "gti:block/ct/turbine/large_turbine_6"
          },
          "rotation": [
            0,
            90,
            0
          ]
        }
      ]
    },
    {
      "id": 14110,
      "models": [
        {
          "parent": "antimatter:block/preset/simple_overlay",
          "textures": {
            "base": "gti:block/ct/turbine/large_turbine_active_6"
          },
          "rotation": [
            0,
            90,
            0
          ]
        }
      ]
    },
    {
      "id": 4010,
      "models": [
        {
          "parent": "antimatter:block/preset/simple_overlay",
          "textures": {
            "base": "gti:block/ct/turbine/large_turbine_7"
          },
          "rotation": [
            0,
            90,
            0
          ]
        }
      ]
    },
    {
      "id": 14010,
      "models": [
        {
          "parent": "antimatter:block/preset/simple_overlay",
          "textures": {
            "base": "gti:block/ct/turbine/large_turbine_active_7"
          },
          "rotation": [
            0,
            90,
            0
          ]
        }
      ]
    },
    {
      "id": 3910,
      "models": [
        {
          "parent": "antimatter:block/preset/simple_overlay",
          "textures": {
            "base": "gti:block/ct/turbine/large_turbine_8"
          },
          "rotation": [
            0,
            90,
            0
          ]
        }
      ]
    },
    {
      "id": 13910,
      "models": [
        {
          "parent": "antimatter:block/preset/simple_overlay",
          "textures": {
            "base": "gti:block/ct/turbine/large_turbine_active_8"
          },
          "rotation": [
            0,
            90,
            0
          ]
        }
      ]
    }
  ],
  "model": {
    "parent": "antimatter:block/preset/simple",
    "textures": {
      "all": "gti:block/casing/turbine_2"
    }
  }
}