{
  "parent": "minecraft:recipes/root",
  "rewards": {
    "recipes": [
      "gti:ingot_electrum_hammer_to_plate_electrum"
    ]
  },
  "criteria": {
    "has_ingot_electrum": {
      "trigger": "minecraft:inventory_changed",
      "conditions": {
        "items": [
          {
            "tag": "forge:ingots/electrum"
          }
        ]
      }
    },
    "has_the_recipe": {
      "trigger": "minecraft:recipe_unlocked",
      "conditions": {
        "recipe": "gti:ingot_electrum_hammer_to_plate_electrum"
      }
    }
  },
  "requirements": [
    [
      "has_ingot_electrum",
      "has_the_recipe"
    ]
  ]
}